automatic_spike_detection-1.3.3.dist-info/licenses/LICENSE
spidet/__init__.py
spidet/domain/ActivationFunction.py
spidet/domain/Artifacts.py
spidet/domain/BadTimesType.py
spidet/domain/BasisFunction.py
spidet/domain/DetectedEvent.py
spidet/domain/FunctionType.py
spidet/domain/Nmfsc.py
spidet/domain/Trace.py
spidet/domain/__init__.py
spidet/load/__init__.py
spidet/load/data_loading.py
spidet/preprocess/__init__.py
spidet/preprocess/artifact_detection.py
spidet/preprocess/filtering.py
spidet/preprocess/preprocessing.py
spidet/preprocess/resampling.py
spidet/preprocess/rescaling.py
spidet/save/nmf_data.py
spidet/spike_detection/__init__.py
spidet/spike_detection/clustering.py
spidet/spike_detection/line_length.py
spidet/spike_detection/nmf.py
spidet/spike_detection/spike_detection_pipeline.py
spidet/spike_detection/thresholding.py
spidet/utils/__init__.py
spidet/utils/data_utils.py
spidet/utils/h5_utils.py
spidet/utils/logging_utils.py
spidet/utils/plotting_utils.py
spidet/utils/times_utils.py
spidet/utils/variables.py
automatic_spike_detection-1.3.3.dist-info/METADATA
automatic_spike_detection-1.3.3.dist-info/WHEEL
automatic_spike_detection-1.3.3.dist-info/top_level.txt
automatic_spike_detection-1.3.3.dist-info/RECORD
