Metadata-Version: 2.4
Name: automatic-spike-detection
Version: 1.3.3
Summary: Python library for automatically detecting interictal epileptiform discharges (IEDs) by means of nonnegative matrix factorization (NMF)
Home-page: https://github.com/domfre/automatic-spike-detection
Author: Dominik Frey
Requires-Python: >=3.9
License-File: LICENSE
Requires-Dist: h5py
Requires-Dist: loguru
Requires-Dist: matplotlib
Requires-Dist: mne
Requires-Dist: mypy-extensions
Requires-Dist: nimfa
Requires-Dist: numpy
Requires-Dist: pandas
Requires-Dist: scikit-learn
Requires-Dist: scipy
Requires-Dist: typing-extensions
Dynamic: license-file
